deepSI/__init__.py
deepSI/fitting.py
deepSI/models.py
deepSI/networks.py
deepSI/normalization.py
deepsi-0.4.4.dist-info/LICENSE
deepsi-0.4.4.dist-info/METADATA
deepsi-0.4.4.dist-info/WHEEL
deepsi-0.4.4.dist-info/RECORD
