Metadata-Version: 2.3
Name: deepSI
Version: 0.4.4
Summary: Data-driven learning of dynamical system in the SUBNET structure and ANNs
License: BSD 3-Clause License
Author: Gerben I. Beintema
Requires-Python: >=3.10,<4.0
Classifier: License :: Other/Proprietary License
Classifier: Programming Language :: Python :: 3
Classifier: Programming Language :: Python :: 3.10
Classifier: Programming Language :: Python :: 3.11
Classifier: Programming Language :: Python :: 3.12
Classifier: Programming Language :: Python :: 3.13
Requires-Dist: cloudpickle
Requires-Dist: nonlinear_benchmarks (>=0.1.2,<0.2.0)
Requires-Dist: numpy (>=1.25)
Requires-Dist: torch (>=2.0.0,<3.0.0)
Requires-Dist: tqdm (>=4.0.0,<5.0.0)
Project-URL: Homepage, https://github.com/GerbenBeintema/deepSI
